relative_mode_index.py
setup.py
src/__init__.py
src/cqhc.py
src/relative_mode.py
relative_mode-0.0.3.dist-info/METADATA
relative_mode-0.0.3.dist-info/WHEEL
relative_mode-0.0.3.dist-info/licenses/LICENSE
relative_mode-0.0.3.dist-info/RECORD
