Metadata-Version: 2.1
Name: relative_mode
Version: 0.0.3
Summary: Relative Mode Estimation from audio files.
Project-URL: Homepage, https://github.com/tuomaseerola/relative_mode
Project-URL: Bug Tracker, https://github.com/tuomaseerola/relative_mode/issues
Author-email: Tuomas Eerola <tuomaseerola39@gmail.com>
License-File: LICENSE
Classifier: License :: OSI Approved :: MIT License
Classifier: Operating System :: OS Independent
Classifier: Programming Language :: Python :: 3
Requires-Python: >=3.9
